gen_ai_hub/__init__.py
gen_ai_hub/orchestration/__init__.py
gen_ai_hub/orchestration/exceptions.py
gen_ai_hub/orchestration/service.py
gen_ai_hub/orchestration/sse_client.py
gen_ai_hub/orchestration/utils.py
gen_ai_hub/orchestration/models/__init__.py
gen_ai_hub/orchestration/models/azure_content_filter.py
gen_ai_hub/orchestration/models/base.py
gen_ai_hub/orchestration/models/config.py
gen_ai_hub/orchestration/models/content_filter.py
gen_ai_hub/orchestration/models/content_filtering.py
gen_ai_hub/orchestration/models/data_masking.py
gen_ai_hub/orchestration/models/document_grounding.py
gen_ai_hub/orchestration/models/llama_guard_3_filter.py
gen_ai_hub/orchestration/models/llm.py
gen_ai_hub/orchestration/models/message.py
gen_ai_hub/orchestration/models/response.py
gen_ai_hub/orchestration/models/response_format.py
gen_ai_hub/orchestration/models/sap_data_privacy_integration.py
gen_ai_hub/orchestration/models/template.py
gen_ai_hub/orchestration/models/template_ref.py
gen_ai_hub/prompt_registry/__init__.py
gen_ai_hub/prompt_registry/client.py
gen_ai_hub/prompt_registry/models/__init__.py
gen_ai_hub/prompt_registry/models/prompt_template.py
gen_ai_hub/proxy/__init__.py
gen_ai_hub/proxy/core/__init__.py
gen_ai_hub/proxy/core/base.py
gen_ai_hub/proxy/core/proxy_clients.py
gen_ai_hub/proxy/core/utils.py
gen_ai_hub/proxy/gen_ai_hub_proxy/__init__.py
gen_ai_hub/proxy/gen_ai_hub_proxy/client.py
gen_ai_hub/proxy/langchain/__init__.py
gen_ai_hub/proxy/langchain/amazon.py
gen_ai_hub/proxy/langchain/base.py
gen_ai_hub/proxy/langchain/google_vertexai.py
gen_ai_hub/proxy/langchain/init_models.py
gen_ai_hub/proxy/langchain/openai.py
gen_ai_hub/proxy/native/__init__.py
gen_ai_hub/proxy/native/amazon/__init__.py
gen_ai_hub/proxy/native/amazon/clients.py
gen_ai_hub/proxy/native/google_vertexai/__init__.py
gen_ai_hub/proxy/native/google_vertexai/clients.py
gen_ai_hub/proxy/native/google_vertexai/streaming.py
gen_ai_hub/proxy/native/google_vertexai/transport.py
generative_ai_hub_sdk-4.4.3.dist-info/LICENSE
generative_ai_hub_sdk-4.4.3.dist-info/METADATA
generative_ai_hub_sdk-4.4.3.dist-info/WHEEL
generative_ai_hub_sdk-4.4.3.dist-info/top_level.txt
generative_ai_hub_sdk-4.4.3.dist-info/RECORD
