Metadata-Version: 2.1
Name: generative-ai-hub-sdk
Version: 4.4.3
Summary: generative AI hub SDK
Home-page: https://www.sap.com/
Author: SAP SE
License: SAP DEVELOPER LICENSE AGREEMENT
Download-URL: https://pypi.python.org/pypi/generative-ai-hub-sdk
Keywords: SAP generative AI hub SDK,SAP AI Core API,SAP AI Core
Platform: Windows
Platform: Linux
Platform: Mac OS-X
Platform: Unix
Classifier: Development Status :: 5 - Production/Stable
Classifier: Intended Audience :: Developers
Classifier: License :: Other/Proprietary License
Classifier: Operating System :: MacOS :: MacOS X
Classifier: Operating System :: Microsoft :: Windows :: Windows 10
Classifier: Operating System :: Microsoft :: Windows :: Windows 7
Classifier: Operating System :: Microsoft :: Windows :: Windows 8
Classifier: Operating System :: Microsoft :: Windows :: Windows 8.1
Classifier: Operating System :: Microsoft :: Windows :: Windows Server 2008
Classifier: Operating System :: POSIX :: Linux
Classifier: Programming Language :: Python
Classifier: Programming Language :: Python :: 3
Classifier: Programming Language :: Python :: 3.9
Classifier: Programming Language :: Python :: 3.10
Classifier: Programming Language :: Python :: 3.11
Classifier: Programming Language :: Python :: 3.12
Classifier: Topic :: Software Development :: Libraries :: Python Modules
Requires-Python: >=3.9
Requires-Dist: click (>=8.1.7)
Requires-Dist: dacite (>=1.8.1)
Requires-Dist: httpx (>=0.27.0)
Requires-Dist: ai-core-sdk (>=2.5.7)
Requires-Dist: overloading (==0.5.0)
Requires-Dist: pydantic (==2.9.2)
Requires-Dist: openai (>=1.56.0)
Requires-Dist: packaging (>=23.2)
Provides-Extra: all
Requires-Dist: langchain (~=0.3.0) ; extra == 'all'
Requires-Dist: langchain-openai (>=0.2.14) ; extra == 'all'
Requires-Dist: langchain-community (~=0.3.0) ; extra == 'all'
Requires-Dist: langchain-aws (==0.2.1) ; extra == 'all'
Requires-Dist: google-cloud-aiplatform (==1.61.0) ; extra == 'all'
Requires-Dist: langchain-google-vertexai (==2.0.1) ; extra == 'all'
Requires-Dist: boto3 (==1.35.27) ; extra == 'all'
Provides-Extra: amazon
Requires-Dist: boto3 (==1.35.27) ; extra == 'amazon'
Provides-Extra: google
Requires-Dist: google-cloud-aiplatform (==1.61.0) ; extra == 'google'
Provides-Extra: langchain
Requires-Dist: langchain (~=0.3.0) ; extra == 'langchain'
Requires-Dist: langchain-openai (>=0.2.14) ; extra == 'langchain'
Requires-Dist: langchain-community (~=0.3.0) ; extra == 'langchain'
Requires-Dist: langchain-aws (==0.2.1) ; extra == 'langchain'
Requires-Dist: langchain-google-vertexai (==2.0.1) ; extra == 'langchain'
